docs/conf.py
examples/warcscrape.py
warc/__init__.py
warc/arc.py
warc/utils.py
warc/warc.py
warc_knot-0.2.5.dist-info/METADATA
warc_knot-0.2.5.dist-info/WHEEL
warc_knot-0.2.5.dist-info/licenses/LICENSE
warc_knot-0.2.5.dist-info/RECORD
