Metadata-Version: 2.1
Name: warc-knot
Version: 0.2.5
Summary: Python library to work with ARC, WARC and WET files
Project-URL: Homepage, https://github.com/KNOT-FIT-BUT/warc3
Project-URL: Bug Tracker, https://github.com/KNOT-FIT-BUT/warc3/issues
Author: Anand Chitipothu, Noufal Ibrahim, Ryan Chartier, Jan Pieter Bruins Slot, Almer S. Tigelaar, Willian Zhang, Michal Šmahel
License-File: LICENSE
Classifier: Environment :: Web Environment
Classifier: Intended Audience :: Developers
Classifier: License :: OSI Approved :: GNU General Public License v2 (GPLv2)
Classifier: Operating System :: OS Independent
Classifier: Programming Language :: Python :: 3
Requires-Python: >=3.3
